py_validate_email/__init__.py
py_validate_email/email_validator.py
py_validate_email-1.0.2.dist-info/DESCRIPTION.rst
py_validate_email-1.0.2.dist-info/METADATA
py_validate_email-1.0.2.dist-info/RECORD
py_validate_email-1.0.2.dist-info/WHEEL
py_validate_email-1.0.2.dist-info/entry_points.txt
py_validate_email-1.0.2.dist-info/metadata.json
py_validate_email-1.0.2.dist-info/top_level.txt
